<vector android:height="110dp" android:viewportHeight="511"
    android:viewportWidth="512" android:width="110dp" xmlns:android="http://schemas.android.com/apk/res/android">
    <path android:fillColor="#4f7693" android:pathData="m416.621,298.832c0,-88.934 -71.918,-161.031 -160.629,-161.031 -88.711,0 -160.629,72.098 -160.629,161.031 0,88.934 71.918,161.031 160.629,161.031 88.711,0 160.629,-72.098 160.629,-161.031zM416.621,298.832"/>
    <path android:fillColor="#fff" android:pathData="m382.059,298.832c0,-69.801 -56.441,-126.383 -126.066,-126.383s-126.066,56.582 -126.066,126.383c0,69.797 56.441,126.383 126.066,126.383s126.066,-56.586 126.066,-126.383zM382.059,298.832"/>
    <path android:fillColor="#e9edf1" android:pathData="m255.992,172.449c-40.527,0 -76.586,19.176 -99.645,48.969 21.293,-16.488 47.992,-26.301 76.977,-26.301 69.625,0 126.066,56.582 126.066,126.383 0,29.168 -9.863,56.027 -26.422,77.414 29.855,-23.113 49.09,-59.344 49.09,-100.082 0,-69.801 -56.441,-126.383 -126.066,-126.383zM255.992,172.449"/>
    <path android:fillColor="#ff84a7" android:pathData="m255.992,293.203c-4.27,0 -7.727,-3.457 -7.727,-7.727v-70.762c0,-4.266 3.461,-7.727 7.727,-7.727 4.27,0 7.727,3.461 7.727,7.727v70.762c0,4.266 -3.457,7.727 -7.727,7.727zM255.992,293.203"/>
    <path android:fillColor="#ff84a7" android:pathData="m317.066,377.344c-2.168,0 -4.324,-0.91 -5.852,-2.68l-52.41,-60.488c-2.785,-3.234 -2.426,-8.113 0.805,-10.898 3.23,-2.789 8.109,-2.43 10.898,0.801l52.406,60.492c2.785,3.23 2.426,8.109 -0.805,10.895 -1.457,1.262 -3.254,1.879 -5.043,1.879zM317.066,377.344"/>
    <path android:fillColor="#ef6085" android:pathData="m273.168,298.832c0,-9.508 -7.691,-17.219 -17.176,-17.219 -9.484,0 -17.176,7.711 -17.176,17.219 0,9.508 7.691,17.219 17.176,17.219 9.484,0 17.176,-7.711 17.176,-17.219zM273.168,298.832"/>
    <path android:fillColor="#8fe5ac" android:pathData="m512,425.219c0,23.898 -9.727,45.523 -25.445,61.105v0.012c-15.484,15.359 -36.797,24.855 -60.316,24.855 -23.422,0 -44.668,-9.426 -60.141,-24.695 -15.809,-15.594 -25.617,-37.281 -25.617,-61.277 0,-47.48 38.398,-85.977 85.758,-85.977 47.363,0 85.762,38.496 85.762,85.977zM512,425.219"/>
    <path android:fillColor="#80cfa1" android:pathData="m426.238,339.242c-5.559,0 -10.984,0.551 -16.25,1.563 39.59,7.617 69.508,42.508 69.508,84.414 0,23.898 -9.727,45.523 -25.441,61.105v0.012c-11.828,11.73 -27.059,20.023 -44.066,23.297 5.266,1.012 10.695,1.559 16.25,1.559 23.52,0 44.832,-9.496 60.316,-24.855v-0.012c15.719,-15.582 25.445,-37.203 25.445,-61.105 0,-47.48 -38.398,-85.977 -85.762,-85.977zM426.238,339.242"/>
    <path android:fillColor="#159856" android:pathData="m486.555,486.324v0.012c-15.484,15.359 -36.797,24.855 -60.316,24.855 -23.422,0 -44.668,-9.426 -60.141,-24.691 1.129,-4.898 3.879,-9.402 7.859,-13.059 5.609,-5.168 13.105,-7.785 20.723,-7.785h63.332c7.629,0 15.117,2.617 20.734,7.785 3.918,3.617 6.66,8.043 7.809,12.883zM486.555,486.324"/>
    <path android:fillColor="#148449" android:pathData="m486.555,486.324c-1.148,-4.84 -3.891,-9.262 -7.813,-12.883 -2.984,-2.746 -6.504,-4.746 -10.281,-6.043 -3.926,6.965 -8.773,13.34 -14.406,18.926v0.012c-11.828,11.73 -27.059,20.023 -44.066,23.297 2.621,0.504 5.285,0.895 7.984,1.156 0.211,0.02 0.426,0.027 0.641,0.047 1.137,0.102 2.277,0.195 3.426,0.25 1.391,0.066 2.793,0.105 4.199,0.105 11.762,0 22.969,-2.375 33.172,-6.668 10.203,-4.293 19.402,-10.508 27.145,-18.188zM486.555,486.324"/>
    <path android:fillColor="#fff" android:pathData="m441.809,427.852 l-9.66,5.902c-3.563,2.18 -8.039,2.18 -11.605,0l-9.656,-5.902c-3.328,-2.031 -5.359,-5.66 -5.359,-9.57v-25.93c0,-7.129 5.758,-12.91 12.859,-12.91h15.918c7.102,0 12.859,5.781 12.859,12.91v25.93c0,3.91 -2.027,7.539 -5.355,9.57zM441.809,427.852"/>
    <path android:fillColor="#8fe5ac" android:pathData="m171.52,425.219c0,23.898 -9.727,45.523 -25.445,61.105v0.012c-15.484,15.359 -36.797,24.855 -60.313,24.855 -23.426,0 -44.668,-9.426 -60.141,-24.695 -15.813,-15.594 -25.621,-37.281 -25.621,-61.277 0,-47.48 38.398,-85.977 85.762,-85.977 47.359,0 85.758,38.496 85.758,85.977zM171.52,425.219"/>
    <path android:fillColor="#80cfa1" android:pathData="m85.762,339.242c-5.563,0 -10.988,0.551 -16.254,1.563 39.59,7.617 69.512,42.508 69.512,84.414 0,23.898 -9.73,45.523 -25.445,61.105v0.012c-11.828,11.73 -27.059,20.023 -44.066,23.297 5.266,1.012 10.695,1.559 16.254,1.559 23.516,0 44.828,-9.496 60.313,-24.855v-0.012c15.719,-15.582 25.445,-37.207 25.445,-61.105 0,-47.48 -38.398,-85.977 -85.758,-85.977zM85.762,339.242"/>
    <path android:fillColor="#159856" android:pathData="m146.074,486.324v0.012c-15.484,15.359 -36.797,24.855 -60.313,24.855 -23.426,0 -44.668,-9.426 -60.141,-24.691 1.125,-4.898 3.875,-9.402 7.859,-13.059 5.605,-5.168 13.105,-7.785 20.719,-7.785h63.336c7.625,0 15.113,2.617 20.73,7.785 3.922,3.617 6.66,8.043 7.809,12.883zM146.074,486.324"/>
    <path android:fillColor="#148449" android:pathData="m146.074,486.324c-1.148,-4.84 -3.887,-9.262 -7.809,-12.883 -2.984,-2.746 -6.504,-4.746 -10.285,-6.043 -3.922,6.965 -8.77,13.34 -14.406,18.926v0.012c-11.828,11.73 -27.055,20.023 -44.066,23.297h0.004c2.621,0.504 5.281,0.895 7.98,1.156 0.211,0.02 0.43,0.027 0.641,0.047 1.137,0.102 2.277,0.195 3.426,0.25 1.395,0.066 2.793,0.105 4.203,0.105 11.758,0 22.965,-2.375 33.168,-6.668 10.207,-4.293 19.406,-10.508 27.145,-18.188zM146.074,486.324"/>
    <path android:fillColor="#fff" android:pathData="m101.328,427.852 l-9.656,5.902c-3.566,2.18 -8.043,2.18 -11.609,0l-9.656,-5.902c-3.328,-2.031 -5.359,-5.66 -5.359,-9.57v-25.93c0,-7.129 5.758,-12.91 12.859,-12.91h15.922c7.102,0 12.859,5.781 12.859,12.91v25.93c0,3.91 -2.031,7.539 -5.359,9.57zM101.328,427.852"/>
    <path android:fillColor="#fdb659" android:pathData="m341.859,86.477c0,23.902 -9.727,45.523 -25.445,61.105v0.012c-15.484,15.359 -36.797,24.855 -60.316,24.855 -23.422,0 -44.668,-9.426 -60.141,-24.691 -15.809,-15.598 -25.617,-37.285 -25.617,-61.281 0,-47.48 38.398,-85.977 85.758,-85.977 47.363,0 85.762,38.496 85.762,85.977zM341.859,86.477"/>
    <path android:fillColor="#fd9e28" android:pathData="m256.098,0.5c-5.559,0 -10.984,0.551 -16.25,1.563 39.59,7.617 69.508,42.504 69.508,84.41 0,23.902 -9.727,45.523 -25.445,61.105v0.016c-11.824,11.73 -27.055,20.023 -44.063,23.293 5.266,1.016 10.691,1.563 16.25,1.563 23.52,0 44.832,-9.496 60.316,-24.855v-0.016c15.719,-15.582 25.445,-37.203 25.445,-61.105 0,-47.477 -38.398,-85.973 -85.762,-85.973zM256.098,0.5"/>
    <path android:fillColor="#ff7e09" android:pathData="m316.414,147.582v0.012c-15.484,15.359 -36.797,24.855 -60.316,24.855 -23.422,0 -44.668,-9.426 -60.141,-24.691 1.129,-4.902 3.879,-9.406 7.859,-13.059 5.609,-5.168 13.105,-7.785 20.723,-7.785h63.332c7.625,0 15.113,2.617 20.734,7.785 3.922,3.617 6.66,8.039 7.809,12.883zM316.414,147.582"/>
    <path android:fillColor="#ea6a0a" android:pathData="m316.414,147.582c-1.148,-4.844 -3.891,-9.266 -7.813,-12.883 -2.984,-2.746 -6.504,-4.75 -10.285,-6.043 -3.922,6.965 -8.77,13.34 -14.406,18.926v0.012c-11.824,11.73 -27.055,20.023 -44.063,23.297 2.621,0.504 5.285,0.891 7.984,1.156 0.211,0.02 0.426,0.027 0.641,0.047 1.137,0.102 2.277,0.191 3.426,0.25 1.391,0.066 2.793,0.105 4.199,0.105 11.762,0 22.969,-2.375 33.172,-6.668s19.402,-10.508 27.145,-18.188zM316.414,147.582"/>
    <path android:fillColor="#fff" android:pathData="m271.668,89.109 l-9.66,5.902c-3.563,2.176 -8.039,2.176 -11.605,0l-9.66,-5.902c-3.324,-2.035 -5.355,-5.66 -5.355,-9.574v-25.926c0,-7.133 5.758,-12.91 12.859,-12.91h15.918c7.102,0 12.859,5.781 12.859,12.91v25.926c0,3.914 -2.027,7.539 -5.355,9.574zM271.668,89.109"/>
</vector>
