<vector android:height="23dp" android:viewportHeight="445.9712"
    android:viewportWidth="445" android:width="23dp"
    xmlns:aapt="http://schemas.android.com/aapt" xmlns:android="http://schemas.android.com/apk/res/android">
    <path android:pathData="m425.809,377.973h-18.316v-142.512c0,-26.465 -21.117,-48.488 -47.586,-48.488h-97.414v-95.973c0,-4.422 -4.07,-8.027 -8.488,-8.027h-63.023c-4.418,0 -8.488,3.605 -8.488,8.027v95.973h-97.418c-26.469,0 -47.582,22.023 -47.582,48.488v142.512h-18.316c-2.109,0.051 -4.105,0.945 -5.551,2.484 -1.441,1.535 -2.211,3.586 -2.133,5.691v51.801c-0.074,2.09 0.703,4.121 2.148,5.633 1.445,1.508 3.441,2.371 5.535,2.391h406.633c2.09,-0.02 4.086,-0.883 5.531,-2.391 1.449,-1.512 2.223,-3.543 2.152,-5.633v-51.801c0.078,-2.105 -0.691,-4.156 -2.137,-5.691 -1.441,-1.539 -3.441,-2.434 -5.547,-2.484zM198.492,98.973h48v88h-48zM85.074,202.973h274.832c17.648,0 31.586,14.844 31.586,32.488v43.281c-12,2.031 -20.27,8.727 -26.637,14.301 -7,6.129 -12.418,10.969 -24.199,10.969s-17.254,-4.84 -24.25,-10.969c-7.598,-6.652 -17.023,-14.934 -34.816,-14.934 -17.793,0 -27.23,8.281 -34.828,14.934 -7,6.129 -12.512,10.969 -24.289,10.969s-17.301,-4.84 -24.301,-10.969c-7.594,-6.652 -17.047,-14.934 -34.836,-14.934 -17.793,0 -27.246,8.281 -34.84,14.934 -7,6.129 -12.52,10.969 -24.301,10.969s-17.09,-4.84 -24.086,-10.969c-6.352,-5.57 -14.617,-12.273 -26.617,-14.301v-43.281c0,-17.645 13.938,-32.488 31.582,-32.488zM53.492,295.027c6,1.676 10.898,5.508 16.086,10.055 7.594,6.652 16.941,14.93 34.734,14.93s27.191,-8.277 34.789,-14.93c7,-6.129 12.5,-10.969 24.27,-10.969 11.77,0 17.289,4.84 24.285,10.969 7.594,6.652 17.039,14.93 34.832,14.93s27.242,-8.277 34.836,-14.93c7,-6.129 12.52,-10.969 24.301,-10.969s17.301,4.84 24.301,10.969c7.598,6.652 17.047,14.93 34.844,14.93 17.793,0 27.035,-8.277 34.633,-14.93 5.188,-4.547 10.09,-8.379 16.09,-10.059v82.949h-338zM417.492,429.973h-390v-36h390zM417.492,429.973">
        <aapt:attr name="android:fillColor">
            <gradient android:endX="211.49095" android:endY="445.3552"
                android:startX="211.49095" android:startY="-14.317802" android:type="linear">
                <item android:color="#FF00EFD1" android:offset="0"/>
                <item android:color="#FF00ACEA" android:offset="1"/>
            </gradient>
        </aapt:attr>
    </path>
    <path android:pathData="m198.031,71.172c0.238,0.246 0.484,0.492 0.727,0.727 6.34,6.188 14.859,9.641 23.719,9.621h0.531c9.043,-0.113 17.664,-3.84 23.945,-10.348 0.039,-0.039 0.074,-0.078 0.109,-0.117 12.887,-13.91 12.887,-35.398 0,-49.309 -0.039,-0.043 -0.082,-0.09 -0.121,-0.133l-18.723,-19.199c-1.504,-1.543 -3.57,-2.414 -5.727,-2.414s-4.223,0.871 -5.73,2.414l-18.719,19.199c-0.043,0.043 -0.086,0.09 -0.125,0.133 -12.887,13.91 -12.887,35.398 0,49.309 0.035,0.035 0.074,0.074 0.113,0.117zM209.566,32.711 L222.492,19.453 235.414,32.711c7.109,7.738 7.109,19.633 0,27.371 -6.965,7.117 -18.375,7.262 -25.52,0.324 -0.109,-0.105 -0.219,-0.215 -0.328,-0.324 -7.109,-7.738 -7.109,-19.633 0,-27.371zM209.566,32.711">
        <aapt:attr name="android:fillColor">
            <gradient android:endX="211.49095" android:endY="445.3552"
                android:startX="211.49095" android:startY="-14.317802" android:type="linear">
                <item android:color="#FF00EFD1" android:offset="0"/>
                <item android:color="#FF00ACEA" android:offset="1"/>
            </gradient>
        </aapt:attr>
    </path>
</vector>
